{
  "project_info": {
    "project_number": "1001518408555",
    "firebase_url": "https://tictactoe-moviles.firebaseio.com",
    "project_id": "tictactoe-moviles",
    "storage_bucket": "tictactoe-moviles.appspot.com"
  },
  "client": [
    {
      "client_info": {
        "mobilesdk_app_id": "1:1001518408555:android:5199765c2ab6917137e22e",
        "android_client_info": {
          "package_name": "co.edu.unal.tictactoe"
        }
      },
      "oauth_client": [
        {
          "client_id": "1001518408555-hgrbh5710dg6emprcc9qh1b8fkicesiv.apps.googleusercontent.com",
          "client_type": 3
        }
      ],
      "api_key": [
        {
          "current_key": "AIzaSyAIfFEZfXcc-Fta-rZJu5Sb9mvlWr85F_A"
        }
      ],
      "services": {
        "appinvite_service": {
          "other_platform_oauth_client": [
            {
              "client_id": "1001518408555-hgrbh5710dg6emprcc9qh1b8fkicesiv.apps.googleusercontent.com",
              "client_type": 3
            }
          ]
        }
      }
    }
  ],
  "configuration_version": "1"
}